deform_markdown-0.2.5.dist-info/top_level.txt
deform_markdown-0.2.5.dist-info/RECORD
deform_markdown-0.2.5.dist-info/METADATA
deform_markdown-0.2.5.dist-info/WHEEL
deform_markdown-0.2.5.dist-info/DESCRIPTION.rst
deform_markdown-0.2.5.dist-info/metadata.json
deform_markdown/test_init.py
deform_markdown/__init__.py
deform_markdown/__pycache__/test_init.cpython-34-PYTEST.pyc
deform_markdown/__pycache__/test_init.cpython-27-PYTEST.pyc
deform_markdown/__pycache__/__init__.cpython-34.pyc
