Metadata-Version: 2.0
Name: deform-markdown
Version: 0.2.5
Summary: Deform widget using 'simplemde' markdown editor to edit TextArea fields.
Home-page: https://github.com/liqd/deform_markdown
Author: Joscha Krutzki
Author-email: joka@jokasis.de
License: ISCL
Keywords: deform_markdown
Platform: UNKNOWN
Classifier: Development Status :: 2 - Pre-Alpha
Classifier: Intended Audience :: Developers
Classifier: License :: OSI Approved :: ISC License (ISCL)
Classifier: Natural Language :: English
Classifier: Programming Language :: Python :: 2
Classifier: Programming Language :: Python :: 2.7
Classifier: Programming Language :: Python :: 3
Classifier: Programming Language :: Python :: 3.4
Classifier: Programming Language :: Python :: 3.5
Requires-Dist: deform
